cumo/.gitignore
cumo/__init__.py
cumo/__main__.py
cumo/_internal/.gitignore
cumo/_internal/__init__.py
cumo/_internal/down_sample.py
cumo/_internal/members/__init__.py
cumo/_internal/members/camera.py
cumo/_internal/members/capture_screen.py
cumo/_internal/members/custom_control.py
cumo/_internal/members/event_handler.py
cumo/_internal/members/internal_utils.py
cumo/_internal/members/keyboard_event_handler.py
cumo/_internal/members/remove_object.py
cumo/_internal/members/send_object.py
cumo/_internal/members/set_config.py
cumo/_internal/members/set_custom_control.py
cumo/_internal/members/set_enable.py
cumo/_internal/members/utils.py
cumo/_internal/protobuf/__init__.py
cumo/_internal/protobuf/client_pb2.py
cumo/_internal/protobuf/client_pb2.pyi
cumo/_internal/protobuf/server_pb2.py
cumo/_internal/protobuf/server_pb2.pyi
cumo/_internal/server.py
cumo/_vendor/pypcd/LICENSE
cumo/_vendor/pypcd/pypcd.py
cumo/camera_state.py
cumo/constants.py
cumo/keyboard_event.py
cumo/pointcloudviewer.py
cumo/public/bundle-ae6d6217.js
cumo/public/bundle.js.LICENSE.txt
cumo/public/index-b6d42797.css
cumo/public/index.html
cumo-0.34.1.dist-info/METADATA
cumo-0.34.1.dist-info/WHEEL
cumo-0.34.1.dist-info/RECORD
