Metadata-Version: 2.1
Name: cumo
Version: 0.34.1
Summary: Webブラウザ上に点群を描画する python ライブラリ
Home-page: https://github.com/kurusugawa-computer/cumo
License: BSD
Keywords: point-cloud,pcd
Author: Kurusugawa Computer
Requires-Python: >=3.7,<4.0
Classifier: Development Status :: 3 - Alpha
Classifier: Intended Audience :: Developers
Classifier: License :: OSI Approved :: BSD License
Classifier: License :: Other/Proprietary License
Classifier: Operating System :: OS Independent
Classifier: Programming Language :: Python
Classifier: Programming Language :: Python :: 3
Classifier: Programming Language :: Python :: 3.7
Classifier: Programming Language :: Python :: 3.8
Classifier: Programming Language :: Python :: 3.9
Classifier: Programming Language :: Python :: 3.10
Classifier: Programming Language :: Python :: 3.11
Classifier: Programming Language :: Python :: 3.12
Classifier: Programming Language :: Python :: 3.13
Classifier: Programming Language :: Python :: 3 :: Only
Classifier: Topic :: Utilities
Requires-Dist: Pillow (>=9,<10)
Requires-Dist: numpy (>=1,<2)
Requires-Dist: protobuf (>=4,<5)
Requires-Dist: python-lzf (>=0.2.4,<0.3.0)
Requires-Dist: types-protobuf (>=4.24.0.1,<5.0.0.0)
Requires-Dist: websockets (>=8,<12)
Project-URL: Repository, https://github.com/kurusugawa-computer/cumo
